{
	"pages": [ //pages数组中第一项表示应用启动页，参考：https://uniapp.dcloud.io/collocation/pages
		
		{
		    "path" : "pages/plan/plan_old",
		    "style" :                                                                                    
		    {
		        "navigationBarTitleText": "计划",
		        "enablePullDownRefresh": false
		    }
		},
		{
		    "path" : "pages/questionnaire/first",
		    "style" :                                                                                    
		    {
		        "navigationBarTitleText": "疾病类型",
		        "enablePullDownRefresh": false
		    }
		    
		},
		{
		    "path" : "pages/mypage/mypage",
		    "style" :                                                                                    
		    {
		        "navigationBarTitleText": "个人中心",
		        "enablePullDownRefresh": false
		    }
		    
		},
		{
		    "path" : "pages/video/video",
		    "style" :                                                                                    
		    {
		        "navigationBarTitleText": "视频",
		        "enablePullDownRefresh": false
		    }
		},
		{
			"path":"pages/plan/report",
			"style":{
				"navigationBarTitleText":"课程报告",
				"enablePullDownRefresh":true
			}
		},
		{
		    "path" : "pages/questionnaire/selectPlan",
		    "style" :                                                                                    
		    {
		        "navigationBarTitleText": "选择方案",
		        "enablePullDownRefresh": false
		    }
		},
		{
			"path": "pages/course/course",
			"style": {
				"navigationBarTitleText": "课程",
				"enablePullDownRefresh": false
				}
		}
		,
		{
		    "path" : "pages/dayExercise/dayExercise",
		    "style" :                                                                                    
		    {
		        "navigationBarTitleText": "日程锻炼报告",
		        "enablePullDownRefresh": false
		    }
		},
		{
		    "path" : "pages/login/login",
		    "style" :                                                                                    
		    {
		        "navigationBarTitleText": "登陆",
		        "enablePullDownRefresh": false
		    }
		},
		{
			"path": "pages/market/market",
			"style": 
			{
				"navigationBarTitleText": "商城",
				"enablePullDownRefresh": true
			}
		},
		{
			"path": "pages/chat/chat",
			"style":
			{
				"navigationBarTitleText": "聊天",
				"enablePullDownRefresh": false
			}
		}
        ,{
            "path" : "pages/questionnaire/questionnaire",
            "style" :                                                                                    
            {
                "navigationBarTitleText": "问卷",
                "enablePullDownRefresh": false
            }
            
        }
        
    ],
	"globalStyle": {
		"navigationBarTextStyle": "black",
		"navigationBarTitleText": "uni-app",
		"navigationBarBackgroundColor": "#F8F8F8",
		"backgroundColor": "#F8F8F8",
		"enablePullDownRefresh":true
		
	},
	"tabBar":{
		"list":[
			{
				"text":"首页",
				"pagePath":"pages/plan/plan_old",
				"iconPath":"static/plan.png",
				"selectedIconPath":"static/plan_active.png"
			},
			{
				"text": "商城",
				"pagePath": "pages/market/market",
				"iconPath": "static/market.png",
				"selectedIconPath": "static/market-active.png"
			},
			{
				"text": "聊天",
				"pagePath": "pages/chat/chat",
				"iconPath": "static/chat.png",
				"selectedIconPath": "static/chat-active.png"
			},
			{
				"text":"我的",
				"pagePath":"pages/mypage/mypage",
				"iconPath":"static/mypage.png",
				"selectedIconPath":"static/mypage-active.png"
			}
		]
	}
}
